mlreflect/__init__.py
mlreflect/version.py
mlreflect/curve_fitter/__init__.py
mlreflect/curve_fitter/base_fitter.py
mlreflect/curve_fitter/curve_fitter.py
mlreflect/curve_fitter/fio_fitter.py
mlreflect/curve_fitter/minimizer.py
mlreflect/curve_fitter/results.py
mlreflect/curve_fitter/spec_fitter.py
mlreflect/data_generation/__init__.py
mlreflect/data_generation/data_generator.py
mlreflect/data_generation/distributions.py
mlreflect/data_generation/interpolation.py
mlreflect/data_generation/layers.py
mlreflect/data_generation/model_mixer.py
mlreflect/data_generation/multilayer.py
mlreflect/data_generation/noise.py
mlreflect/data_generation/parameters.py
mlreflect/data_generation/reflectivity.py
mlreflect/models/__init__.py
mlreflect/models/model_helpers.py
mlreflect/models/simple_model.py
mlreflect/models/trained_model.py
mlreflect/resources/example/example.dat
mlreflect/resources/example/example.spec
mlreflect/resources/models/default_trained_model_with_absorption.h5
mlreflect/resources/models/different_model.h5
mlreflect/training/__init__.py
mlreflect/training/footprint.py
mlreflect/training/noise_generator.py
mlreflect/training/prediction.py
mlreflect/training/preprocessing.py
mlreflect/training/training.py
mlreflect/utils/__init__.py
mlreflect/utils/check_gpu.py
mlreflect/utils/h5_tools.py
mlreflect/utils/label_helpers.py
mlreflect/utils/naming.py
mlreflect/utils/performance_tools.py
mlreflect/xrrloader/__init__.py
mlreflect/xrrloader/dataloader/__init__.py
mlreflect/xrrloader/dataloader/exceptions.py
mlreflect/xrrloader/dataloader/fio_loader.py
mlreflect/xrrloader/dataloader/reflectivity_loader.py
mlreflect/xrrloader/dataloader/scans.py
mlreflect/xrrloader/dataloader/spec_loader.py
mlreflect/xrrloader/dataloader/transform.py
mlreflect/xrrloader/footprint/__init__.py
mlreflect/xrrloader/footprint/footprint.py
mlreflect/xrrloader/footprint/normalization.py
mlreflect/xrrloader/p08tools/P08ScanTools.py
mlreflect/xrrloader/p08tools/__init__.py
mlreflect-0.21.1.dist-info/LICENSE
mlreflect-0.21.1.dist-info/METADATA
mlreflect-0.21.1.dist-info/WHEEL
mlreflect-0.21.1.dist-info/top_level.txt
mlreflect-0.21.1.dist-info/RECORD
